gpu_info-2.0.1.dist-info/DESCRIPTION.rst
gpu_info-2.0.1.dist-info/METADATA
gpu_info-2.0.1.dist-info/RECORD
gpu_info-2.0.1.dist-info/WHEEL
gpu_info-2.0.1.dist-info/metadata.json
gpu_info-2.0.1.dist-info/top_level.txt
gpuinfo/__init__.py
gpuinfo/nvidia.py
gpuinfo/windows.py
