Metadata-Version: 2.0
Name: gpu-info
Version: 2.0.1
Summary: An intuitive and Pythonic GPU interface.
Home-page: https://github.com/Avlyssna/gpu-info
Author: Avlyssna
Author-email: avlyssna@gmail.com
License: MIT
Keywords: GPU GPUs Graphics
Platform: UNKNOWN
